<?xml version="1.0" encoding="UTF-8" standalone="yes"?>
<messages>
    <message>
        <content>hxfhgh</content>
        <recipient>juanje@gmail.com</recipient>
        <sender>alfonsojaen2005@gmail.com</sender>
        <timestamp>2024-10-25 09:51:29</timestamp>
    </message>
    <message>
        <content>555555555555555</content>
        <recipient>juanje@gmail.com</recipient>
        <sender>alfonsojaen2005@gmail.com</sender>
        <timestamp>2024-10-25 09:53:25</timestamp>
    </message>
    <message>
        <content>HOla</content>
        <recipient>juanje@gmail.com</recipient>
        <sender>alfonsojaen2005@gmail.com</sender>
        <timestamp>2024-10-25 09:56:38</timestamp>
    </message>
</messages>
